buildaspider/__init__.py
buildaspider/spider.py
buildaspider/spiderconfig.py
buildaspider-0.9.3.dist-info/LICENSE
buildaspider-0.9.3.dist-info/WHEEL
buildaspider-0.9.3.dist-info/METADATA
buildaspider-0.9.3.dist-info/RECORD
