Metadata-Version: 2.1
Name: buildaspider
Version: 0.9.3
Summary: Build yourself a small site crawler.
License: MIT
Author: Joe Dougherty
Author-email: joseph.dougherty@gmail.com
Requires-Python: >=3.6,<4.0
Classifier: Development Status :: 4 - Beta
Classifier: Intended Audience :: Developers
Classifier: Intended Audience :: Education
Classifier: License :: OSI Approved :: MIT License
Classifier: Operating System :: POSIX :: Linux
Classifier: Programming Language :: Python :: 3
Classifier: Programming Language :: Python :: 3.6
Classifier: Programming Language :: Python :: 3.7
Classifier: Programming Language :: Python :: 3.8
Classifier: Topic :: Education
Requires-Dist: bs4 (>=0.0.1,<0.0.2)
Requires-Dist: prettytable (>=0.7.2,<0.8.0)
Requires-Dist: requests (>=2.24.0,<3.0.0)
